lazyapi/__init__.py
lazyapi/classes.py
lazyapi/client.py
lazyapi/config.py
lazyapi/fast.py
lazyapi/retry.py
lazyapi/services.py
lazyapi/timez.py
lazyapi/utils.py
lazyapi-0.0.4.dist-info/LICENSE
lazyapi-0.0.4.dist-info/METADATA
lazyapi-0.0.4.dist-info/WHEEL
lazyapi-0.0.4.dist-info/top_level.txt
lazyapi-0.0.4.dist-info/RECORD
