Metadata-Version: 2.1
Name: lazyapi
Version: 0.0.4
Summary: Async and Sync wrapper client around httpx
Home-page: https://github.com/trisongz/lazyapi
Author: Tri Songz
Author-email: ts@growthengineai.com
License: MIT Style
Platform: UNKNOWN
Classifier: Intended Audience :: Developers
Classifier: License :: OSI Approved :: MIT License
Classifier: Programming Language :: Python :: 3.7
Classifier: Topic :: Software Development :: Libraries
License-File: LICENSE
Requires-Dist: httpx
Requires-Dist: lazycls
Requires-Dist: pytz
Requires-Dist: dateparser
Requires-Dist: fastapi
Requires-Dist: starlette
Requires-Dist: six
Requires-Dist: diskcache
Requires-Dist: msgpack
Requires-Dist: pylogz
